pylogos/__init__.py
pylogos/translate.py
pylogos/algorithm/BST.py
pylogos/algorithm/MRP.py
pylogos/algorithm/TMT.py
pylogos/algorithm/__init__.py
pylogos/algorithm/string_builder.py
pylogos/query_graph/__init__.py
pylogos/query_graph/koutrika_query_graph.py
pylogos/query_graph/queryGraph.py
pylogos/template/__init__.py
pylogos/template/generic_template.py
pylogos/template/kourtrika_template.py
pylogos/template/specific_template_student.py
pylogos/template/template.py
pylogos/template/schema_templates/schema_template_cars_data.py
pylogos/template/schema_templates/schema_template_concert_singer.py
pylogos/template/schema_templates/schema_template_student.py
pylogos-0.1.17.dist-info/METADATA
pylogos-0.1.17.dist-info/WHEEL
pylogos-0.1.17.dist-info/RECORD
