Metadata-Version: 2.1
Name: pylogos
Version: 0.1.17
Summary: A collection of useful util functions
Project-URL: Homepage, https://github.com/hyukkyukang/logos_python
Project-URL: Bug Tracker, https://github.com/hyukkyukang/logos_python/issues
Author-email: Hyukkyu Kang <hyukkyukang@gmail.com>
Classifier: License :: OSI Approved :: MIT License
Classifier: Operating System :: OS Independent
Classifier: Programming Language :: Python :: 3
Requires-Python: >=3.7
Requires-Dist: matplotlib>=3.6
Requires-Dist: networkx>=2.8
Requires-Dist: numpy>=1.23
Requires-Dist: pglast>=3.17
Requires-Dist: unittest-xml-reporting>=3.2
